{"css_bfc布局.md":"D3zhVSHq","css_css 滤镜.md":"BlGqDpOp","css_css优先级.md":"C5SEf-pF","css_flex 布局.md":"C-RUGXnS","css_js in css.md":"DivOkPih","css_两球相交.md":"kbtYg37-","css_层叠系统.md":"BrylqO8Q","css_星型评价.md":"ygNZansR","english_conversations_how to ask and reply to basic questions.md":"CNjvTZXL","english_places and travel_how to ask someone where they are from.md":"BLtuxUh9","english_punctuation marks_the apostrophe.md":"B1I03vzp","english_punctuation marks_the comma.md":"Bdam20yW","english_punctuation marks_the period_ the question mark_ and the exclamation point.md":"DfPN-v2j","index.md":"Dtv0ePum","javascript_array.md":"D6l6M6Vm","javascript_async 与 await原理.md":"C2HKhtTq","javascript_clone-deep.md":"De4qeGsy","javascript_decorator.md":"5aI97z_f","javascript_ejs.md":"D42Y_m0n","javascript_es5继承实现.md":"Ce9JwlrE","javascript_es6设计模式.md":"C50ImTmN","javascript_es特性_es10.md":"CjoA7Jhq","javascript_es特性_es7.md":"6NRQ5h73","javascript_es特性_es8.md":"C2jRtTlB","javascript_es特性_es9.md":"BsPPRq0v","javascript_es特性_object.md":"Cwt1FSg2","javascript_es特性_proxy.md":"D9m901il","javascript_es特性_symbol.md":"D4zhNabp","javascript_for-in与object-keys的区别.md":"BLHsEzUc","javascript_ioc控制翻转.md":"ero2qvo0","javascript_js位运算.md":"CRlVxNyL","javascript_js原型链.md":"Du6jI5MP","javascript_js堆栈执行原理.md":"CBVLBTYn","javascript_map and weekmap.md":"COLJZqFI","javascript_nan和isnan.md":"D1KFvhwB","javascript_new class vs new function.md":"D6oeb1ue","javascript_promise-async-poll.md":"E0vIUeyG","javascript_promise_promise相关的函数.md":"CrW7Rn00","javascript_promise_promise规范.md":"U1On9cXZ","javascript_promise_手写promise.md":"DSPRD082","javascript_reflect.md":"BlpASQGc","javascript_symbol.md":"DWWI3UpY","javascript_tc39提案意义.md":"DCTZGcfD","javascript_判断和处理数组.md":"B0RG3M4w","javascript_原理instanceof.md":"Ble-dWsa","javascript_原理typeof.md":"WY0TmFQy","javascript_变量与函数提升.md":"CuYB8Dze","javascript_常用函数式编程库.md":"Bfe-wMQB","javascript_模块历史.md":"CjiTB53m","javascript_运算优先级.md":"CwyJFAO_","javascript_隐式类型转换.md":"CQPe0-E6","javascript_面向切面编程.md":"DdGL3h7N","readme.md":"C1q6tUeL","其他_bloglist.md":"pm2NbLsT","其他_formula.md":"BUooEUJa","其他_领域模型.md":"DLI2JVD6","后端_jsp.md":"IJ495lTq","后端_mysql.md":"0X77JMxg","后端_php.md":"Bgm6abR4","工具_iterm2配置.md":"BQ-va1yk","工具_jest-debugger.md":"Ctr_ur5I","工具_latex公式.md":"CjMJKjc2","工具_markdown-examples.md":"DzLFZ7Vn","工具_markdown.md":"V1DxqOGi","工具_mermaid笔记.md":"BoW2x9vO","工具_pasteimage.md":"DwlsS01e","工具_visual-studio-code-terminal-command.md":"NrE_LByc","工具_vitepress配置.md":"DQ9aeS1k","工程化_angularjs_angular-ui路由权限篇.md":"CNL7NxLf","工程化_angularjs_angularjs绑定html标签.md":"DWD7U9_z","工程化_angularjs_angular服务篇.md":"CSmsn78D","工程化_babel.md":"B4FvBY79","工程化_circleci.md":"DuQ5yB-I","工程化_docker.md":"Dqo4vBx8","工程化_git-submodule.md":"DNoNJT0V","工程化_gogs-之-docker-ssh-通信（mac）.md":"DbEqxVpA","工程化_hmr原理.md":"BQS_oph9","工程化_jenkins安装.md":"DHvDKQXJ","工程化_linux.md":"DAAMxxx_","工程化_loader与plugin.md":"S5X9IJU-","工程化_mac常用操作.md":"BmYOewsf","工程化_nginx.md":"oXEi3mB5","工程化_ngrok内网穿透.md":"DBRUy_py","工程化_node_avn自动切换node版本.md":"Bpx5jOyi","工程化_node_koa_koa安装swig.md":"BgNha2oM","工程化_node_nodejs事件流.md":"BGyCkYmS","工程化_node_npm 安装程序使用国内镜像.md":"Du3v-xWM","工程化_node_npm-install-时总是报phantomjs-prebuilt-2-1-14安装失败.md":"Dpf9UyWe","工程化_node_npm命令.md":"BaNbjhGb","工程化_node_package.json中的sideeffects 属性的作用.md":"Bqrb6MU-","工程化_node_v8源码解析_isolate.md":"CKXC4Ucd","工程化_node_v8源码解析_v8执行流程.md":"Dibgc7D9","工程化_npm scripts 设置环境变量.md":"DJEGwCsZ","工程化_pm2原理.md":"CNWqPBAu","工程化_react_jotai 状态管理.md":"CPJQbGQr","工程化_react_props不可变性.md":"9ntY3iFl","工程化_react_react ref 操作与使用场景.md":"C8neyBNl","工程化_react_react-hook.md":"C3xJqVOm","工程化_react_react性能优化的方法.md":"lF_lsIAH","工程化_react_react状态管理工具.md":"_PZ-rrMS","工程化_react_recoil 状态管理.md":"D4XgN4IJ","工程化_react_redux 状态管理.md":"mXeZYwMx","工程化_react_usestate如何更新数据.md":"DFBThOom","工程化_react_zustand 状态管理.md":"BGQyMcat","工程化_sonarqube.md":"euIlYmT8","工程化_ssh.md":"C_eu0iih","工程化_ssh基本操作.md":"C8G_wQcz","工程化_vue_vue-diff算法.md":"Bt05G9CE","工程化_vue_vue-router原理解析.md":"Dqgrj37K","工程化_vue_vue3 beta 新优势.md":"BNEBhbs8","工程化_vue_vue3的domdiff和vdom优化.md":"BWBfUTeg","工程化_vue_vue解析-defineproperty与proxy.md":"Dum1rCTN","工程化_webpack插件.md":"B_hYC4cc","工程化_webrtc-peerjs.md":"s0_72iN7","工程化_代码提及规范.md":"CMBLOXpO","工程化_生成ssh.md":"Cf5Kj6BT","性能优化_图片懒加载.md":"CY5-2-5G","性能优化_图片类型解析.md":"BnSbHOeC","性能优化_浏览器缓存.md":"BUd_KUBI","测试_ui测试之backstopjs.md":"BpQ3GEFL","浏览器_0.1_0.2.md":"BQ1eiTOS","浏览器_beforeupload和upload.md":"M3QK83wz","浏览器_canvas.md":"8kaMpTgJ","浏览器_cookie使用的方法与属性详解.md":"DZhWl38C","浏览器_cors-简单请求与复杂请求.md":"CI5E5_O6","浏览器_css重回重排.md":"5cHm9aLY","浏览器_html调邮箱手机.md":"B8YgX7A9","浏览器_http2.0.md":"D2MtGVi3","浏览器_http协议.md":"Dpd5QHTr","浏览器_http状态码.md":"CaOx4hEl","浏览器_keycode 对照表.md":"Duu6-6zF","浏览器_src和href的区别.md":"DP6zQ9Ud","浏览器_syn攻击.md":"DSWDbw_h","浏览器_tls握手.md":"BLPX-qeL","浏览器_一帧发生了什么.md":"Co9QG2Lf","浏览器_中间人攻击.md":"CZd-0qt7","浏览器_事件代理.md":"C3Yu5-2_","浏览器_前端统计如何实现数据传递.md":"tdEYFmC3","浏览器_小程序canvas签名.md":"C8rxj8dn","浏览器_小程序分包加载.md":"BdOLVFI4","浏览器_微前端弃用iframe.md":"BWHhs6k2","浏览器_渲染流程.md":"Z-vXGiuF","浏览器_移动端适配方案和对比.md":"B_PmqeAB","算法_lru页面置换算法.md":"CXqqLAOc","算法_斐波那契数列的求法.md":"D1od2UZu","算法_树形数据结构转换.md":"CBhlY9va","算法_统计-1-n-整数中出现-1-的次数.md":"DqK-KPwJ"}
